{"code": ["Require Import List.", "Import ListNotations.", "Require Import Undecidability.Synthetic.Undecidability.", "From Undecidability.Shared.Libs.DLW Require Import utils.", "From Undecidability.PCP Require Import PCP.", "From Undecidability.StackMachines Require Import BSM iPCPb_to_BSM_HALTING.", "From Undecidability.MinskyMachines Require Import MM BSM_MM.", "Import ReductionChainNotations UndecidabilityNotations.", "Lemma iBPCP_chain_MM : \u23a9iPCPb \u2aaf\u2098 BSM_HALTING \u2aaf\u2098 MM_HALTS_ON_ZERO\u23ad.", "Proof.", "msplit 1.", "+", "apply iPCPb_to_BSM_HALTING.", "+", "apply BSM_MM_HALTS_ON_ZERO.", "Qed.", "Lemma iBPCP_to_MM : iPCPb \u2aaf MM_HALTS_ON_ZERO.", "Proof.", "reduce with chain iBPCP_chain_MM.", "Qed."], "theorems": [{"name": "iBPCP_chain_MM", "kind": "Lemma", "begin": 8, "end": 15}, {"name": "iBPCP_to_MM", "kind": "Lemma", "begin": 16, "end": 19}]}