{"code": ["Require Import Lia.", "Require Import ssreflect ssrbool ssrfun.", "Set Default Goal Selector \"!\".", "Lemma measure_ind {X : Type} (f : X -> nat) (P : X -> Prop) : (forall x, (forall y, f y < f x -> P y) -> P x) -> forall (x : X), P x.", "Proof.", "apply : well_founded_ind.", "apply : Wf_nat.well_founded_lt_compat.", "move => *.", "by eassumption.", "Qed.", "Arguments measure_ind {X}.", "Lemma measure_rect {X : Type} (f : X -> nat) (P : X -> Type) : (forall x, (forall y, f y < f x -> P y) -> P x) -> forall (x : X), P x.", "Proof.", "apply : well_founded_induction_type.", "apply : Wf_nat.well_founded_lt_compat.", "move => *.", "by eassumption.", "Qed.", "Arguments measure_rect {X}.", "Lemma copy {A : Prop} : A -> A * A.", "Proof.", "done.", "Qed.", "Lemma unnest (X Y Z: Type): X -> (Y -> Z) -> (X -> Y) -> Z.", "Proof.", "by auto.", "Qed."], "theorems": [{"name": "measure_ind", "kind": "Lemma", "begin": 3, "end": 9}, {"name": "measure_rect", "kind": "Lemma", "begin": 11, "end": 17}, {"name": "copy", "kind": "Lemma", "begin": 19, "end": 22}, {"name": "unnest", "kind": "Lemma", "begin": 23, "end": 26}]}